Workbook

Sheet Dashboard
C3: 🌿 FARM PROFITABILITY & RESOURCE TRACKING DASHBOARD
C4: Season: Summer 2025/26 | Mixed Vegetable Production
C6: Selected Farm :
C7: Boland Veggie Farm
C9: Total Revenue | F9: Total Input Cost® | I9: Gross Profit ® | L9: Profit Margin(%)
C10: =SUMIF(Yield_Log!D4:D30,C7,Yield_Log!K4:K30) -> 68580 | F10: =SUMIF(Yield_Log!D4:D30,C7,Yield_Log!L4:L30) -> 22500 | I10: =SUMIF(Yield_Log!D4:D30,C7,Yield_Log!M4:M30) -> 46080 | L10: =IFERROR(I10/C10,0) -> 0.67191601
C13: Crop | D13: Total Revenue ® | E13: Total Input Cost® | F13: Gross Profit® | G13: Profit Margin(%)
C14: Tomatoes | D14: =SUMIFS(Yield_Log!K4:K30,Yield_Log!D4:D30,$C$7,Yield_Log!G4:G30,C14) -> 0 | E14: =SUMIFS(Yield_Log!L4:L30,Yield_Log!D4:D30,$C$7,Yield_Log!G4:G30,C14) -> 0 | F14: =SUMIFS(Yield_Log!M4:M30,Yield_Log!D4:D30,$C$7,Yield_Log!G4:G30,C14) -> 0 | G14: =SUMIFS(Yield_Log!N5:N31,Yield_Log!D5:D31,$C$7,Yield_Log!G5:G31,C14) -> 0
C15: Spinach | D15: =SUMIFS(Yield_Log!K5:K31,Yield_Log!D5:D31,$C$7,Yield_Log!G5:G31,C15) -> 0 | E15: =SUMIFS(Yield_Log!L5:L31,Yield_Log!D5:D31,$C$7,Yield_Log!G5:G31,C15) -> 0 | F15: =SUMIFS(Yield_Log!M5:M31,Yield_Log!D5:D31,$C$7,Yield_Log!G5:G31,C15) -> 0 | G15: =SUMIFS(Yield_Log!N6:N32,Yield_Log!D6:D32,$C$7,Yield_Log!G6:G32,C15) -> 0
C16: Cabbage | D16: =SUMIFS(Yield_Log!K6:K32,Yield_Log!D6:D32,$C$7,Yield_Log!G6:G32,C16) -> 0 | E16: =SUMIFS(Yield_Log!L6:L32,Yield_Log!D6:D32,$C$7,Yield_Log!G6:G32,C16) -> 0 | F16: =SUMIFS(Yield_Log!M6:M32,Yield_Log!D6:D32,$C$7,Yield_Log!G6:G32,C16) -> 0 | G16: =SUMIFS(Yield_Log!N7:N33,Yield_Log!D7:D33,$C$7,Yield_Log!G7:G33,C16) -> 0
C17: Butternut | D17: =SUMIFS(Yield_Log!K7:K33,Yield_Log!D7:D33,$C$7,Yield_Log!G7:G33,C17) -> 23920 | E17: =SUMIFS(Yield_Log!L7:L33,Yield_Log!D7:D33,$C$7,Yield_Log!G7:G33,C17) -> 7100 | F17: =SUMIFS(Yield_Log!M7:M33,Yield_Log!D7:D33,$C$7,Yield_Log!G7:G33,C17) -> 16820 | G17: =SUMIFS(Yield_Log!N8:N34,Yield_Log!D8:D34,$C$7,Yield_Log!G8:G34,C17) -> 0.70317726
C18: Green pepper | D18: =SUMIFS(Yield_Log!K8:K34,Yield_Log!D8:D34,$C$7,Yield_Log!G8:G34,C18) -> 0 | E18: =SUMIFS(Yield_Log!L8:L34,Yield_Log!D8:D34,$C$7,Yield_Log!G8:G34,C18) -> 0 | F18: =SUMIFS(Yield_Log!M8:M34,Yield_Log!D8:D34,$C$7,Yield_Log!G8:G34,C18) -> 0 | G18: =SUMIFS(Yield_Log!N9:N35,Yield_Log!D9:D35,$C$7,Yield_Log!G9:G35,C18) -> 0
C19: Onion | D19: =SUMIFS(Yield_Log!K9:K35,Yield_Log!D9:D35,$C$7,Yield_Log!G9:G35,C19) -> 0 | E19: =SUMIFS(Yield_Log!L9:L35,Yield_Log!D9:D35,$C$7,Yield_Log!G9:G35,C19) -> 0 | F19: =SUMIFS(Yield_Log!M9:M35,Yield_Log!D9:D35,$C$7,Yield_Log!G9:G35,C19) -> 0 | G19: =SUMIFS(Yield_Log!N10:N36,Yield_Log!D10:D36,$C$7,Yield_Log!G10:G36,C19) -> 0
C20: Carrot | D20: =SUMIFS(Yield_Log!K10:K36,Yield_Log!D10:D36,$C$7,Yield_Log!G10:G36,C20) -> 17160 | E20: =SUMIFS(Yield_Log!L10:L36,Yield_Log!D10:D36,$C$7,Yield_Log!G10:G36,C20) -> 5600 | F20: =SUMIFS(Yield_Log!M10:M36,Yield_Log!D10:D36,$C$7,Yield_Log!G10:G36,C20) -> 11560 | G20: =SUMIFS(Yield_Log!N11:N37,Yield_Log!D11:D37,$C$7,Yield_Log!G11:G37,C20) -> 0.67365967
C21: Broccoli | D21: =SUMIFS(Yield_Log!K11:K37,Yield_Log!D11:D37,$C$7,Yield_Log!G11:G37,C21) -> 0 | E21: =SUMIFS(Yield_Log!L11:L37,Yield_Log!D11:D37,$C$7,Yield_Log!G11:G37,C21) -> 0 | F21: =SUMIFS(Yield_Log!M11:M37,Yield_Log!D11:D37,$C$7,Yield_Log!G11:G37,C21) -> 0 | G21: =SUMIFS(Yield_Log!N12:N38,Yield_Log!D12:D38,$C$7,Yield_Log!G12:G38,C21) -> 0
C22: Watermelon | D22: =SUMIFS(Yield_Log!K12:K38,Yield_Log!D12:D38,$C$7,Yield_Log!G12:G38,C22) -> 0 | E22: =SUMIFS(Yield_Log!L12:L38,Yield_Log!D12:D38,$C$7,Yield_Log!G12:G38,C22) -> 0 | F22: =SUMIFS(Yield_Log!M12:M38,Yield_Log!D12:D38,$C$7,Yield_Log!G12:G38,C22) -> 0 | G22: =SUMIFS(Yield_Log!N13:N39,Yield_Log!D13:D39,$C$7,Yield_Log!G13:G39,C22) -> 0
C23: Sweet potato | D23: =SUMIFS(Yield_Log!K13:K39,Yield_Log!D13:D39,$C$7,Yield_Log!G13:G39,C23) -> 0 | E23: =SUMIFS(Yield_Log!L13:L39,Yield_Log!D13:D39,$C$7,Yield_Log!G13:G39,C23) -> 0 | F23: =SUMIFS(Yield_Log!M13:M39,Yield_Log!D13:D39,$C$7,Yield_Log!G13:G39,C23) -> 0 | G23: =SUMIFS(Yield_Log!M23:M49,Yield_Log!C23:C49,$C$7,Yield_Log!F23:F49,C23) -> 0

Sheet Input_Log
C3: Entry ID | D3: Date | E3: Farm Name | F3: Province | G3: Season | H3: Input Category | I3: Input Item | J3: Quantity Used | K3: Unit | L3: Unit Cost (R) | M3: Total Cost (ZAR) | N3: Budgeted Amount (R) | O3: Variance (ZAR)
C4: E001 | D4: 05/10/2024 | E4: Sunrise Farm | F4: =VLOOKUP(E4,Lookup_Tables!$C:$D,2,0) -> Limpopo | G4: Summer 2025/26 | H4: Seeds | I4: Tomato Seeds (F1 Hybrid) | J4: 5 | K4: kg | L4: 420 | M4: =(J4*L4) -> 2100 | N4: 2500 | O4: =(M4-N4) -> -400 | V4: Sunrise Farm
C5: E002 | D5: 05/10/2024 | E5: Sunrise Farm | F5: =VLOOKUP(E5,Lookup_Tables!$C:$D,2,0) -> Limpopo | G5: Summer 2025/26 | H5: Seeds | I5: Spinach Seeds | J5: 3 | K5: kg | L5: 180 | M5: =(J5*L5) -> 540 | N5: 600 | O5: =(M5-N5) -> -60 | V5: Hlalani Agri
C6: E003 | D6: 07/10/2024 | E6: Sunrise Farm | F6: =VLOOKUP(E6,Lookup_Tables!$C:$D,2,0) -> Limpopo | G6: Summer 2025/26 | H6: Fertilizer | I6: LAN Fertilizer 28% | J6: 50 | K6: kg | L6: 14.5 | M6: =(J6*L6) -> 725 | N6: 750 | O6: =(M6-N6) -> -25 | V6: Boland Veggie Farm
C7: E004 | D7: 08/10/2024 | E7: Sunrise Farm | F7: =VLOOKUP(E7,Lookup_Tables!$C:$D,2,0) -> Limpopo | G7: summer 2025/26 | H7: Labour | I7: Land Preparation Labour | J7: 8 | K7: day | L7: 350 | M7: =(J7*L7) -> 2800 | N7: 3000 | O7: =(M7-N7) -> -200 | V7: Khanya Farm
C8: E005 | D8: 10/10/2024 | E8: Sunrise Farm | F8: =VLOOKUP(E8,Lookup_Tables!$C:$D,2,0) -> Limpopo | G8: Summer 2025/26 | H8: Irrigation | I8: Drip Tape Rolls | J8: 10 | K8: roll | L8: 280 | M8: =(J8*L8) -> 2800 | N8: 3000 | O8: =(M8-N8) -> -200 | V8: Lesedi Plots
C9: E006 | D9: 12/10/2024 | E9: Hlalani Agri | F9: =VLOOKUP(E9,Lookup_Tables!$C:$D,2,0) -> Kwa-Zulu-Natal | G9: summer | H9: Seeds | I9: Cabbage Seeds (Hybrid) | J9: 4 | K9: kg | L9: 390 | M9: =(J9*L9) -> 1560 | N9: 1800 | O9: =(M9-N9) -> -240 | V9: Nkosi Holdings
C10: E007 | D10: 12/10/2024 | E10: Hlalani Agri | F10: =VLOOKUP(E10,Lookup_Tables!$C:$D,2,0) -> Kwa-Zulu-Natal | G10: summer | H10: Fertilizer | I10: Compound D Fertilizer | J10: 80 | K10: kg | L10: 12.8 | M10: =(J10*L10) -> 1024 | N10: 1100 | O10: =(M10-N10) -> -76 | V10: Kalahari Fresh
C11: E008 | D11: 14/10/2024 | E11: Hlalani Agri | F11: =VLOOKUP(E11,Lookup_Tables!$C:$D,2,0) -> Kwa-Zulu-Natal | G11: summer | H11: Pesticide | I11: Aphid Control Spray | J11: 5 | K11: litre | L11: 220 | M11: =(J11*L11) -> 1100 | N11: 1200 | O11: =(M11-N11) -> -100 | V11: Coastal Greens
C12: E009 | D12: 14/10/2024 | E12: Hlalani Agri | F12: =VLOOKUP(E12,Lookup_Tables!$C:$D,2,0) -> Kwa-Zulu-Natal | G12: summer | H12: Labour | I12: Planting Labour | J12: 10 | K12: day | L12: 320 | M12: =(J12*L12) -> 3200 | N12: 3500 | O12: =(M12-N12) -> -300 | V12: Free State Harvest
C13: E010 | D13: 16/10/2024 | E13: Hlalani Agri | F13: =VLOOKUP(E13,Lookup_Tables!$C:$D,2,0) -> Kwa-Zulu-Natal | G13: summer | H13: Transport | I13: Produce Delivery to Market | J13: 3 | K13: trip | L13: 450 | M13: =(J13*L13) -> 1350 | N13: 1500 | O13: =(M13-N13) -> -150
C14: E011 | D14: 18/10/2024 | E14: Boland Veggie Farm | F14: =VLOOKUP(E14,Lookup_Tables!$C:$D,2,0) -> Western Cape | G14: summer | H14: Seeds | I14: Butternut Seeds | J14: 6 | K14: kg | L14: 310 | M14: =(J14*L14) -> 1860 | N14: 2000 | O14: =(M14-N14) -> -140
C15: E012 | D15: 18/10/2024 | E15: Boland Veggie Farm | F15: =VLOOKUP(E15,Lookup_Tables!$C:$D,2,0) -> Western Cape | G15: summer | H15: Fertilizer | I15: Urea 46% | J15: 60 | K15: kg | L15: 16.2 | M15: =(J15*L15) -> 972 | N15: 1050 | O15: =(M15-N15) -> -78
C16: E013 | D16: 20/10/2024 | E16: Boland Veggie Farm | F16: =VLOOKUP(E16,Lookup_Tables!$C:$D,2,0) -> Western Cape | G16: summer | H16: Pesticide | I16: Fungicide (Ridomil) | J16: 4 | K16: litre | L16: 380 | M16: =(J16*L16) -> 1520 | N16: 1700 | O16: =(M16-N16) -> -180
C17: E014 | D17: 20/10/2024 | E17: Boland Veggie Farm | F17: =VLOOKUP(E17,Lookup_Tables!$C:$D,2,0) -> Western Cape | G17: summer | H17: Equipment | I17: Irrigation Pump Service | J17: 1 | K17: unit | L17: 1800 | M17: =(J17*L17) -> 1800 | N17: 2000 | O17: =(M17-N17) -> -200
C18: E015 | E18: Boland Veggie Farm | F18: =VLOOKUP(E18,Lookup_Tables!$C:$D,2,0) -> Western Cape | G18: summer | H18: Labour | I18: Weeding Labour | J18: 12 | K18: day | L18: 300 | M18: =(J18*L18) -> 3600 | N18: 4000 | O18: =(M18-N18) -> -400
C19: E016 | D19: 24/10/2024 | E19: Khanya Farm | F19: =VLOOKUP(E19,Lookup_Tables!$C:$D,2,0) -> Gauteng | G19: summer | H19: Seeds | I19: Green Pepper Seeds | J19: 2 | K19: kg | L19: 490 | M19: =(J19*L19) -> 980 | N19: 1100 | O19: =(M19-N19) -> -120
C20: E017 | D20: 24/10/2024 | E20: Khanya Farm | F20: =VLOOKUP(E20,Lookup_Tables!$C:$D,2,0) -> Gauteng | G20: summer | H20: Seeds | I20: Lettuce Seeds | J20: 1 | K20: kg | L20: 650 | M20: =(J20*L20) -> 650 | N20: 700 | O20: =(M20-N20) -> -50
C21: E018 | D21: 26/10/2024 | E21: Khanya Farm | F21: =VLOOKUP(E21,Lookup_Tables!$C:$D,2,0) -> Gauteng | G21: summer | H21: Fertilizer | I21: Potassium Nitrate | J21: 30 | K21: kg | L21: 22 | M21: =(J21*L21) -> 660 | N21: 700 | O21: =(M21-N21) -> -40
C22: E019 | D22: 26/10/2024 | E22: Khanya Farm | F22: =VLOOKUP(E22,Lookup_Tables!$C:$D,2,0) -> Gauteng | G22: summer | H22: Labour | I22: Harvesting Labour | J22: 6 | K22: day | L22: 380 | M22: =(J22*L22) -> 2280 | N22: 2500 | O22: =(M22-N22) -> -220
C23: E020 | D23: 28/10/2024 | E23: Khanya Farm | F23: =VLOOKUP(E23,Lookup_Tables!$C:$D,2,0) -> Gauteng | G23: summer | H23: Packaging | I23: Vegetable Crates | J23: 50 | K23: unit | L23: 45 | M23: =(J23*L23) -> 2250 | N23: 2500 | O23: =(M23-N23) -> -250
C24: E021 | D24: 30/10/2024 | E24: Lesedi Plots | F24: =VLOOKUP(E24,Lookup_Tables!$C:$D,2,0) -> North West | G24: summer | H24: Seeds | I24: Sweet Potato Cuttings | J24: 20 | K24: kg | L24: 85 | M24: =(J24*L24) -> 1700 | N24: 2000 | O24: =(M24-N24) -> -300
C25: E022 | D25: 30/10/2024 | E25: Lesedi Plots | F25: =VLOOKUP(E25,Lookup_Tables!$C:$D,2,0) -> North West | G25: summer | H25: Fertilizer | I25: Superphosphate | J25: 70 | K25: kg | L25: 11.5 | M25: =(J25*L25) -> 805 | N25: 900 | O25: =(M25-N25) -> -95
C26: E023 | D26: 01/11/2024 | E26: Lesedi Plots | F26: =VLOOKUP(E26,Lookup_Tables!$C:$D,2,0) -> North West | G26: summer | H26: Pesticide | I26: Nematicide Treatment | J26: 3 | K26: litre | L26: 410 | M26: =(J26*L26) -> 1230 | N26: 1400 | O26: =(M26-N26) -> -170
C27: E024 | D27: 01/11/2024 | E27: Lesedi Plots | F27: =VLOOKUP(E27,Lookup_Tables!$C:$D,2,0) -> North West | G27: summer | H27: Labour | I27: Irrigation Setup Labour | J27: 5 | K27: day | L27: 340 | M27: =(J27*L27) -> 1700 | N27: 1800 | O27: =(M27-N27) -> -100
C28: E025 | D28: 03/11/2024 | E28: Lesedi Plots | F28: =VLOOKUP(E28,Lookup_Tables!$C:$D,2,0) -> North West | G28: summer | H28: Transport | I28: Input Delivery from Town | J28: 2 | K28: trip | L28: 380 | M28: =(J28*L28) -> 760 | N28: 800 | O28: =(M28-N28) -> -40
C29: E026 | D29: 05/11/2024 | E29: Nkosi Holdings | F29: =VLOOKUP(E29,Lookup_Tables!$C:$D,2,0) -> Mpumalanga | G29: summer | H29: Seeds | I29: Maize Seed (PAN 6Q-308) | J29: 25 | K29: kg | L29: 98 | M29: =(J29*L29) -> 2450 | N29: 2800 | O29: =(M29-N29) -> -350
C30: E027 | D30: 05/11/2024 | E30: Nkosi Holdings | F30: =VLOOKUP(E30,Lookup_Tables!$C:$D,2,0) -> Mpumalanga | G30: summer | H30: Seeds | I30: Groundnut Seed | J30: 15 | K30: kg | L30: 120 | M30: =(J30*L30) -> 1800 | N30: 2000 | O30: =(M30-N30) -> -200
... C53: E050 | D53: 05/12/2024 | E53: Khanya Farm | F53: =VLOOKUP(E53,Lookup_Tables!$C:$D,2,0) -> Gauteng | G53: summer | H53: Irrigation | I53: Water Pump Repair | J53: 1 | K53: unit | L53: 2200 | M53: =(J53*L53) -> 2200 | N53: 2000 | O53: =(M53-N53) -> 200

Sheet Yield_Log
C3: Yield ID | D3: Farm Name | E3: Province | F3: Season | G3: Crop | H3: Area Planted(Ha) | I3: Yield (kg) | J3: Market Price (R/kg) | K3: Total Revenue® | L3: Input Cost® | M3: Gross Profit ® | N3: Profit Margin(%)
C4: Y001 | D4: Sunrise Farm | E4: =VLOOKUP(D4,Lookup_Tables!$C:$D,2,0) -> Limpopo | F4: Summer 2025/26 | G4: Tomatoes | H4: 1.2 | I4: 4800 | J4: 6.5 | K4: =(I4*J4) -> 31200 | L4: 8750 | M4: =(K4-L4) -> 22450 | N4: =IFERROR(M4/K4,0) -> 0.71955128
C5: Y002 | D5: Sunrise Farm | E5: =VLOOKUP(D5,Lookup_Tables!$C:$D,2,0) -> Limpopo | F5: Summer 2025/26 | G5: Spinach | H5: 0.8 | I5: 2400 | J5: 4.2 | K5: =(I5*J5) -> 10080 | L5: 3200 | M5: =(K5-L5) -> 6880 | N5: =IFERROR(M5/K5,0) -> 0.68253968
C6: Y003 | D6: Sunrise Farm | E6: =VLOOKUP(D6,Lookup_Tables!$C:$D,2,0) -> Limpopo | F6: Summer 2025/26 | G6: Sweet Potato | H6: 1 | I6: 3600 | J6: 5.8 | K6: =(I6*J6) -> 20880 | L6: 5400 | M6: =(K6-L6) -> 15480 | N6: =IFERROR(M6/K6,0) -> 0.74137931
C7: Y004 | D7: Hlalani Agri | E7: =VLOOKUP(D7,Lookup_Tables!$C:$D,2,0) -> Kwa-Zulu-Natal | F7: Summer 2025/26 | G7: Cabbage | H7: 1.5 | I7: 6000 | J7: 3.8 | K7: =(I7*J7) -> 22800 | L7: 7200 | M7: =(K7-L7) -> 15600 | N7: =IFERROR(M7/K7,0) -> 0.68421053
C8: Y005 | D8: Hlalani Agri | E8: =VLOOKUP(D8,Lookup_Tables!$C:$D,2,0) -> Kwa-Zulu-Natal | F8: Summer 2025/26 | G8: Spinach | H8: 0.6 | I8: 1800 | J8: 4.2 | K8: =(I8*J8) -> 7560 | L8: 2800 | M8: =(K8-L8) -> 4760 | N8: =IFERROR(M8/K8,0) -> 0.62962963
C9: Y006 | D9: Hlalani Agri | E9: =VLOOKUP(D9,Lookup_Tables!$C:$D,2,0) -> Kwa-Zulu-Natal | F9: Summer 2025/26 | G9: Green Pepper | H9: 0.9 | I9: 2700 | J9: 9.2 | K9: =(I9*J9) -> 24840 | L9: 6500 | M9: =(K9-L9) -> 18340 | N9: =IFERROR(M9/K9,0) -> 0.73832528
C10: Y007 | D10: Boland Veggie Farm | E10: =VLOOKUP(D10,Lookup_Tables!$C:$D,2,0) -> Western Cape | F10: Summer 2025/26 | G10: Broccoli | H10: 1 | I10: 2200 | J10: 12.5 | K10: =(I10*J10) -> 27500 | L10: 9800 | M10: =(K10-L10) -> 17700 | N10: =IFERROR(M10/K10,0) -> 0.64363636
C11: Y008 | D11: Boland Veggie Farm | E11: =VLOOKUP(D11,Lookup_Tables!$C:$D,2,0) -> Western Cape | F11: Summer 2025/26 | G11: Butternut | H11: 1.3 | I11: 5200 | J11: 4.6 | K11: =(I11*J11) -> 23920 | L11: 7100 | M11: =(K11-L11) -> 16820 | N11: =IFERROR(M11/K11,0) -> 0.70317726
C12: Y009 | D12: Boland Veggie Farm | E12: =VLOOKUP(D12,Lookup_Tables!$C:$D,2,0) -> Western Cape | F12: Summer 2025/26 | G12: Carrot | H12: 1.1 | I12: 4400 | J12: 3.9 | K12: =(I12*J12) -> 17160 | L12: 5600 | M12: =(K12-L12) -> 11560 | N12: =IFERROR(M12/K12,0) -> 0.67365967
C13: Y010 | D13: Khanya Farm | E13: =VLOOKUP(D13,Lookup_Tables!$C:$D,2,0) -> Gauteng | F13: Summer 2025/26 | G13: Tomatoes | H13: 0.8 | I13: 3200 | J13: 6.5 | K13: =(I13*J13) -> 20800 | L13: 6200 | M13: =(K13-L13) -> 14600 | N13: =IFERROR(M13/K13,0) -> 0.70192308
C14: Y011 | D14: Khanya Farm | E14: =VLOOKUP(D14,Lookup_Tables!$C:$D,2,0) -> Gauteng | F14: Summer 2025/26 | G14: Green Pepper | H14: 0.7 | I14: 2100 | J14: 9.2 | K14: =(I14*J14) -> 19320 | L14: 5800 | M14: =(K14-L14) -> 13520 | N14: =IFERROR(M14/K14,0) -> 0.69979296
C15: Y012 | D15: Khanya Farm | E15: =VLOOKUP(D15,Lookup_Tables!$C:$D,2,0) -> Gauteng | F15: Summer 2025/26 | G15: Onion | H15: 1 | I15: 4000 | J15: 5.2 | K15: =(I15*J15) -> 20800 | L15: 5200 | M15: =(K15-L15) -> 15600 | N15: =IFERROR(M15/K15,0) -> 0.75
... C30: Y027 | D30: Free State Harvest | E30: =VLOOKUP(D30,Lookup_Tables!$C:$D,2,0) -> Free State | F30: Summer 2025/26 | G30: Butternut | H30: 1 | I30: 4000 | J30: 4.6 | K30: =(I30*J30) -> 18400 | L30: 5800 | M30: =(K30-L30) -> 12600 | N30: =IFERROR(M30/K30,0) -> 0.68478261

Sheet Profitability_Summary
D3: Profitability By Farm | O3: Profitability By Crop
C5: Farm Name | D5: Total Revenue® | E5: Total Input Cost® | F5: Gross Profit ® | G5: Profit Margin(%) | H5: Top Crop | N5: Crop | O5: Total Revenue® | P5: Total Input Cost® | Q5: Gross Profit ® | R5: Profit Margin(%) | S5: Times Grown
C6: Sunrise Farm | D6: =SUMIF(Yield_Log!D4:D30,C6,Yield_Log!K4:K30) -> 62160 | E6: =SUMIF(Yield_Log!D4:D30,C6,Yield_Log!L4:L30) -> 17350 | F6: =(D6-E6) -> 44810 | G6: =ROUND(IFERROR(F6/E6,0),2) -> 2.58 | H6: =INDEX(Yield_Log!G4:G30,MATCH(_xlfn.MAXIFS(Yield_Log!M4:M30,Yield_Log!D4:D30,C6),Yield_Log!M4:M30,0)) -> Tomatoes | N6: Tomatoes | O6: =SUMIF(Yield_Log!G4:G30,N6,Yield_Log!K4:K30) -> 88400 | P6: =SUMIF(Yield_Log!G4:G30,N6,Yield_Log!L4:L30) -> 24150 | Q6: =(O6-P6) -> 64250 | R6: =ROUND(IFERROR(Q6/P6,0),2) -> 2.66 | S6: =COUNTIF(Yield_Log!G4:G30,N6) -> 3
C7: Hlalani Agri | D7: =SUMIF(Yield_Log!D5:D31,C7,Yield_Log!K5:K31) -> 55200 | E7: =SUMIF(Yield_Log!D5:D31,C7,Yield_Log!L5:L31) -> 16500 | F7: =(D7-E7) -> 38700 | G7: =ROUND(IFERROR(F7/E7,0),2) -> 2.35 | H7: =INDEX(Yield_Log!G5:G31,MATCH(_xlfn.MAXIFS(Yield_Log!M5:M31,Yield_Log!D5:D31,C7),Yield_Log!M5:M31,0)) -> Green Pepper | N7: Spinach | O7: =SUMIF(Yield_Log!G5:G31,N7,Yield_Log!K5:K31) -> 8820 | P7: =SUMIF(Yield_Log!G5:G31,N7,Yield_Log!L5:L31) -> 3000 | Q7: =(O7-P7) -> 5820 | R7: =ROUND(IFERROR(Q7/P7,0),2) -> 1.94 | S7: =COUNTIF(Yield_Log!G5:G31,N7) -> 1
C8: Boland Veggie Farm | D8: =SUMIF(Yield_Log!D6:D32,C8,Yield_Log!K6:K32) -> 68580 | E8: =SUMIF(Yield_Log!D6:D32,C8,Yield_Log!L6:L32) -> 22500 | F8: =(D8-E8) -> 46080 | G8: =ROUND(IFERROR(F8/E8,0),2) -> 2.05 | H8: =INDEX(Yield_Log!G6:G32,MATCH(_xlfn.MAXIFS(Yield_Log!M6:M32,Yield_Log!D6:D32,C8),Yield_Log!M6:M32,0)) -> Broccoli | N8: Cabbage | O8: =SUMIF(Yield_Log!G6:G32,N8,Yield_Log!K6:K32) -> 53200 | P8: =SUMIF(Yield_Log!G6:G32,N8,Yield_Log!L6:L32) -> 17200 | Q8: =(O8-P8) -> 36000 | R8: =ROUND(IFERROR(Q8/P8,0),2) -> 2.09 | S8: =COUNTIF(Yield_Log!G6:G32,N8) -> 3
C9: Khanya Farm | D9: =SUMIF(Yield_Log!D7:D33,C9,Yield_Log!K7:K33) -> 60920 | E9: =SUMIF(Yield_Log!D7:D33,C9,Yield_Log!L7:L33) -> 17200 | F9: =(D9-E9) -> 43720 | G9: =ROUND(IFERROR(F9/E9,0),2) -> 2.54 | H9: =INDEX(Yield_Log!G7:G33,MATCH(_xlfn.MAXIFS(Yield_Log!M7:M33,Yield_Log!D7:D33,C9),Yield_Log!M7:M33,0)) -> Cabbage | N9: Butternut | O9: =SUMIF(Yield_Log!G7:G33,N9,Yield_Log!K7:K33) -> 64400 | P9: =SUMIF(Yield_Log!G7:G33,N9,Yield_Log!L7:L33) -> 19700 | Q9: =(O9-P9) -> 44700 | R9: =ROUND(IFERROR(Q9/P9,0),2) -> 2.27 | S9: =COUNTIF(Yield_Log!G7:G33,N9) -> 3
C10: Lesedi Plots | D10: =SUMIF(Yield_Log!D8:D34,C10,Yield_Log!K8:K34) -> 62416 | E10: =SUMIF(Yield_Log!D8:D34,C10,Yield_Log!L8:L34) -> 18500 | F10: =(D10-E10) -> 43916 | G10: =ROUND(IFERROR(F10/E10,0),2) -> 2.37 | H10: =INDEX(Yield_Log!G8:G34,MATCH(_xlfn.MAXIFS(Yield_Log!M8:M34,Yield_Log!D8:D34,C10),Yield_Log!M8:M34,0)) -> Sweet Potato | N10: Green pepper | O10: =SUMIF(Yield_Log!G8:G34,N10,Yield_Log!K8:K34) -> 19320 | P10: =SUMIF(Yield_Log!G8:G34,N10,Yield_Log!L8:L34) -> 5800 | Q10: =(O10-P10) -> 13520 | R10: =ROUND(IFERROR(Q10/P10,0),2) -> 2.33 | S10: =COUNTIF(Yield_Log!G8:G34,N10) -> 1
C11: Nkosi Holdings | D11: =SUMIF(Yield_Log!D9:D35,C11,Yield_Log!K9:K35) -> 71240 | E11: =SUMIF(Yield_Log!D9:D35,C11,Yield_Log!L9:L35) -> 19600 | F11: =(D11-E11) -> 51640 | G11: =ROUND(IFERROR(F11/E11,0),2) -> 2.63 | H11: =INDEX(Yield_Log!G9:G35,MATCH(_xlfn.MAXIFS(Yield_Log!M9:M35,Yield_Log!D9:D35,C11),Yield_Log!M9:M35,0)) -> Tomatoes | N11: Onion | O11: =SUMIF(Yield_Log!G9:G35,N11,Yield_Log!K9:K35) -> 92560 | P11: =SUMIF(Yield_Log!G9:G35,N11,Yield_Log!L9:L35) -> 24600 | Q11: =(O11-P11) -> 67960 | R11: =ROUND(IFERROR(Q11/P11,0),2) -> 2.76 | S11: =COUNTIF(Yield_Log!G9:G35,N11) -> 4
C12: Kalahari Fresh | D12: =SUMIF(Yield_Log!D10:D36,C12,Yield_Log!K10:K36) -> 75440 | E12: =SUMIF(Yield_Log!D10:D36,C12,Yield_Log!L10:L36) -> 22400 | F12: =(D12-E12) -> 53040 | G12: =ROUND(IFERROR(F12/E12,0),2) -> 2.37 | H12: =INDEX(Yield_Log!G10:G36,MATCH(_xlfn.MAXIFS(Yield_Log!M10:M36,Yield_Log!D10:D36,C12),Yield_Log!M10:M36,0)) -> Watermelon | N12: Carrot | O12: =SUMIF(Yield_Log!G10:G36,N12,Yield_Log!K10:K36) -> 49920 | P12: =SUMIF(Yield_Log!G10:G36,N12,Yield_Log!L10:L36) -> 16600 | Q12: =(O12-P12) -> 33320 | R12: =ROUND(IFERROR(Q12/P12,0),2) -> 2.01 | S12: =COUNTIF(Yield_Log!G10:G36,N12) -> 3
C13: Coastal Greens | D13: =SUMIF(Yield_Log!D11:D37,C13,Yield_Log!K11:K37) -> 51810 | E13: =SUMIF(Yield_Log!D11:D37,C13,Yield_Log!L11:L37) -> 17400 | F13: =(D13-E13) -> 34410 | G13: =ROUND(IFERROR(F13/E13,0),2) -> 1.98 | H13: =INDEX(Yield_Log!G11:G37,MATCH(_xlfn.MAXIFS(Yield_Log!M11:M37,Yield_Log!D11:D37,C13),Yield_Log!M11:M37,0)) -> Broccoli | N13: Broccoli | O13: =SUMIF(Yield_Log!G11:G37,N13,Yield_Log!K11:K37) -> 24750 | P13: =SUMIF(Yield_Log!G11:G37,N13,Yield_Log!L11:L37) -> 8600 | Q13: =(O13-P13) -> 16150 | R13: =ROUND(IFERROR(Q13/P13,0),2) -> 1.88 | S13: =COUNTIF(Yield_Log!G11:G37,N13) -> 1
C14: Free State Harvest | D14: =SUMIF(Yield_Log!D12:D38,C14,Yield_Log!K12:K38) -> 68320 | E14: =SUMIF(Yield_Log!D12:D38,C14,Yield_Log!L12:L38) -> 20400 | F14: =(D14-E14) -> 47920 | G14: =ROUND(IFERROR(F14/E14,0),2) -> 2.35 | H14: =INDEX(Yield_Log!G12:G38,MATCH(_xlfn.MAXIFS(Yield_Log!M12:M38,Yield_Log!D12:D38,C14),Yield_Log!M12:M38,0)) -> Onion | N14: Watermelon | O14: =SUMIF(Yield_Log!G12:G38,N14,Yield_Log!K12:K38) -> 58800 | P14: =SUMIF(Yield_Log!G12:G38,N14,Yield_Log!L12:L38) -> 17700 | Q14: =(O14-P14) -> 41100 | R14: =ROUND(IFERROR(Q14/P14,0),2) -> 2.32 | S14: =COUNTIF(Yield_Log!G12:G38,N14) -> 2
C15: Totals | D15: =SUM(D6:D14) -> 576086 | E15: =SUM(E6:E14) -> 171850 | F15: =SUM(F6:F14) -> 404236 | G15: =ROUND(IFERROR(F15/D15,0),4) -> 0.7017 | N15: Sweet potato | O15: =SUMIF(Yield_Log!G13:G39,N15,Yield_Log!K13:K39) -> 25056 | P15: =SUMIF(Yield_Log!G13:G39,N15,Yield_Log!L13:L39) -> 6800 | Q15: =(O15-P15) -> 18256 | R15: =ROUND(IFERROR(Q15/P15,0),2) -> 2.68 | S15: =COUNTIF(Yield_Log!G13:G39,N15) -> 1
N16: Totals | O16: =SUM(O6:O15) -> 485226 | P16: =SUM(P6:P15) -> 144150 | Q16: =SUM(Q6:Q15) -> 341076 | R16: =ROUND(IFERROR(Q15/O15,0),4) -> 0.7286

Sheet Chart_Data
C3: Revenue vs Input Cost by Farm | J3: Revenue by Crop | O3: Profit Margin by Crop
C5: Farm Name | D5: Total Revenue® | E5: Total Input Cost® | F5: Gross Profit ® | J5: Crop | K5: Revenue | O5: Crop | P5: Profit Margin
C6: Sunrise Farm | D6: =SUMIF(Yield_Log!D4:D31,C6,Yield_Log!K4:K30) -> 62160 | E6: =SUMIF(Yield_Log!D4:D30,C6,Yield_Log!L4:L30) -> 17350 | F6: =(D6-E6) -> 44810 | J6: Tomatoes | K6: =SUMIF(Yield_Log!G4:G30,J6,Yield_Log!K4:K30) -> 88400 | O6: Tomatoes | P6: =ROUND(IFERROR(SUMIF(Yield_Log!G4:G30,O6,Yield_Log!M4:M30)/SUMIF(Yield_Log!G4:G30,O6,Yield_Log!K4:K30),0),2) -> 0.73
C7: Hlalani Agri | D7: =SUMIF(Yield_Log!D5:D32,C7,Yield_Log!K5:K31) -> 55200 | E7: =SUMIF(Yield_Log!D5:D31,C7,Yield_Log!L5:L31) -> 16500 | F7: =(D7-E7) -> 38700 | J7: Spinach | K7: =SUMIF(Yield_Log!G5:G31,J7,Yield_Log!K5:K31) -> 8820 | O7: Spinach | P7: =ROUND(IFERROR(SUMIF(Yield_Log!G5:G31,O7,Yield_Log!M5:M31)/SUMIF(Yield_Log!G5:G31,O7,Yield_Log!K5:K31),0),2) -> 0.66
C8: Boland Veggie Farm | D8: =SUMIF(Yield_Log!D6:D33,C8,Yield_Log!K6:K32) -> 68580 | E8: =SUMIF(Yield_Log!D6:D32,C8,Yield_Log!L6:L32) -> 22500 | F8: =(D8-E8) -> 46080 | J8: Cabbage | K8: =SUMIF(Yield_Log!G6:G32,J8,Yield_Log!K6:K32) -> 53200 | O8: Cabbage | P8: =ROUND(IFERROR(SUMIF(Yield_Log!G6:G32,O8,Yield_Log!M6:M32)/SUMIF(Yield_Log!G6:G32,O8,Yield_Log!K6:K32),0),2) -> 0.68
C9: Khanya Farm | D9: =SUMIF(Yield_Log!D7:D34,C9,Yield_Log!K7:K33) -> 60920 | E9: =SUMIF(Yield_Log!D7:D33,C9,Yield_Log!L7:L33) -> 17200 | F9: =(D9-E9) -> 43720 | J9: Butternut | K9: =SUMIF(Yield_Log!G7:G33,J9,Yield_Log!K7:K33) -> 64400 | O9: Butternut | P9: =ROUND(IFERROR(SUMIF(Yield_Log!G7:G33,O9,Yield_Log!M7:M33)/SUMIF(Yield_Log!G7:G33,O9,Yield_Log!K7:K33),0),2) -> 0.69
C10: Lesedi Plots | D10: =SUMIF(Yield_Log!D8:D35,C10,Yield_Log!K8:K34) -> 62416 | E10: =SUMIF(Yield_Log!D8:D34,C10,Yield_Log!L8:L34) -> 18500 | F10: =(D10-E10) -> 43916 | J10: Green pepper | K10: =SUMIF(Yield_Log!G8:G34,J10,Yield_Log!K8:K34) -> 19320 | O10: Green pepper | P10: =ROUND(IFERROR(SUMIF(Yield_Log!G8:G34,O10,Yield_Log!M8:M34)/SUMIF(Yield_Log!G8:G34,O10,Yield_Log!K8:K34),0),2) -> 0.7
C11: Nkosi Holdings | D11: =SUMIF(Yield_Log!D9:D36,C11,Yield_Log!K9:K35) -> 71240 | E11: =SUMIF(Yield_Log!D9:D35,C11,Yield_Log!L9:L35) -> 19600 | F11: =(D11-E11) -> 51640 | J11: Onion | K11: =SUMIF(Yield_Log!G9:G35,J11,Yield_Log!K9:K35) -> 92560 | O11: Onion | P11: =ROUND(IFERROR(SUMIF(Yield_Log!G9:G35,O11,Yield_Log!M9:M35)/SUMIF(Yield_Log!G9:G35,O11,Yield_Log!K9:K35),0),2) -> 0.73
C12: Kalahari Fresh | D12: =SUMIF(Yield_Log!D10:D37,C12,Yield_Log!K10:K36) -> 75440 | E12: =SUMIF(Yield_Log!D10:D36,C12,Yield_Log!L10:L36) -> 22400 | F12: =(D12-E12) -> 53040 | J12: Carrot | K12: =SUMIF(Yield_Log!G10:G36,J12,Yield_Log!K10:K36) -> 49920 | O12: Carrot | P12: =ROUND(IFERROR(SUMIF(Yield_Log!G10:G36,O12,Yield_Log!M10:M36)/SUMIF(Yield_Log!G10:G36,O12,Yield_Log!K10:K36),0),2) -> 0.67
C13: Coastal Greens | D13: =SUMIF(Yield_Log!D11:D38,C13,Yield_Log!K11:K37) -> 51810 | E13: =SUMIF(Yield_Log!D11:D37,C13,Yield_Log!L11:L37) -> 17400 | F13: =(D13-E13) -> 34410 | J13: Broccoli | K13: =SUMIF(Yield_Log!G11:G37,J13,Yield_Log!K11:K37) -> 24750 | O13: Broccoli | P13: =ROUND(IFERROR(SUMIF(Yield_Log!G11:G37,O13,Yield_Log!M11:M37)/SUMIF(Yield_Log!G11:G37,O13,Yield_Log!K11:K37),0),2) -> 0.65
C14: Free State Harvest | D14: =SUMIF(Yield_Log!D12:D39,C14,Yield_Log!K12:K38) -> 68320 | E14: =SUMIF(Yield_Log!D12:D38,C14,Yield_Log!L12:L38) -> 20400 | F14: =(D14-E14) -> 47920 | J14: Watermelon | K14: =SUMIF(Yield_Log!G12:G38,J14,Yield_Log!K12:K38) -> 58800 | O14: Watermelon | P14: =ROUND(IFERROR(SUMIF(Yield_Log!G12:G38,O14,Yield_Log!M12:M38)/SUMIF(Yield_Log!G12:G38,O14,Yield_Log!K12:K38),0),2) -> 0.7
J15: Sweet potato | K15: =SUMIF(Yield_Log!G13:G39,J15,Yield_Log!K13:K39) -> 25056 | O15: Sweet potato | P15: =ROUND(IFERROR(SUMIF(Yield_Log!G13:G39,O15,Yield_Log!M13:M39)/SUMIF(Yield_Log!G13:G39,O15,Yield_Log!K13:K39),0),2) -> 0.73

Sheet Lookup_Tables
C3: Farm Name | D3: Province | E3: Crop | F3: Season
C4: Sunrise Farm | D4: Limpopo | E4: Tomatoes | F4: Summer 2025/26
C5: Hlalani Agri | D5: Kwa-Zulu-Natal | E5: Spinach | F5: Summer 2025/26
C6: Boland Veggie Farm | D6: Western Cape | E6: Cabbage | F6: Summer 2025/26
C7: Khanya Farm | D7: Gauteng | E7: Butternut | F7: Summer 2025/26
C8: Lesedi Plots | D8: North West | E8: Green pepper | F8: Summer 2025/26
C9: Nkosi Holdings | D9: Mpumalanga | E9: Onion | F9: Summer 2025/26
C10: Kalahari Fresh | D10: Northern Cape | E10: Carrot | F10: Summer 2025/26
C11: Coastal Greens | D11: Eastern Cape | E11: Broccoli | F11: Summer 2025/26
C12: Free State Harvest | D12: Free State | E12: Watermelon | F12: Summer 2025/26
E13: Sweet potato
